SafeML/Anderson_Darling_Dist_PVal.py
SafeML/Anderson_Darling_Distance.py
SafeML/CVM_Dist_PVal.py
SafeML/CVM_Distance.py
SafeML/ChernoffDistance.py
SafeML/DTS_Distance.py
SafeML/Kolmogorov_Smirnov_Dist_PVal.py
SafeML/Kolmogorov_Smirnov_Distance.py
SafeML/KuiperDistance.py
SafeML/Kuiper_Dist_PVal.py
SafeML/WassersteinDistance.py
SafeML/Wasserstein_Dist_PVal.py
SafeML/Wilson_Interval_Confidence.py
SafeML/__init__.py
SafeML/setup.py
SafeML-0.3.dist-info/LICENSE
SafeML-0.3.dist-info/METADATA
SafeML-0.3.dist-info/WHEEL
SafeML-0.3.dist-info/top_level.txt
SafeML-0.3.dist-info/RECORD
